libeeepy/__init__.py
libeeepy/calculateaccuracy.py
libeeepy/dataprocessing.py
libeeepy/operatemysql.py
libeeepy-2.0.0.dist-info/METADATA
libeeepy-2.0.0.dist-info/WHEEL
libeeepy-2.0.0.dist-info/top_level.txt
libeeepy-2.0.0.dist-info/RECORD
